infscroll/__init__.py
infscroll/admin.py
infscroll/apps.py
infscroll/models.py
infscroll/tests.py
infscroll/utils.py
infscroll/views.py
infscroll/__pycache__/__init__.cpython-39.pyc
infscroll/__pycache__/admin.cpython-39.pyc
infscroll/__pycache__/apps.cpython-39.pyc
infscroll/__pycache__/models.cpython-39.pyc
infscroll/__pycache__/tests.cpython-39.pyc
infscroll/__pycache__/utils.cpython-39.pyc
infscroll/__pycache__/views.cpython-39.pyc
infscroll/migrations/__init__.py
infscroll/migrations/__pycache__/__init__.cpython-39.pyc
infscroll/static/css/scroll.css
infscroll/static/imgs/uparrow.webp
infscroll/static/js/scroll.js
infscroll/templates/infscroll/more.html
infscroll/templates/infscroll/scroll.html
infscroll/templates/infscroll/scroll_box.html
infscroll/templates/infscroll/scroll_tags.html
django_infinite_scroll-0.1.0.dist-info/LICENSE
django_infinite_scroll-0.1.0.dist-info/METADATA
django_infinite_scroll-0.1.0.dist-info/WHEEL
django_infinite_scroll-0.1.0.dist-info/top_level.txt
django_infinite_scroll-0.1.0.dist-info/RECORD
