Metadata-Version: 2.1
Name: django-infinite-scroll
Version: 0.1.0
Summary: Adds infinite scroll to any page
Home-page: https://github.com/gsteixeira
Author: Gustavo Selbach Teixeira
Author-email: gsteixei@gmail.com
License: GNU License
Platform: UNKNOWN
Classifier: Environment :: Web Environment
Classifier: Framework :: Django
License-File: LICENSE
Requires-Dist: Django (>=3.2.10)
Requires-Dist: django-compressor (>=3.1)
